coolest_package/__init__.py
coolest_package/cities.json
coolest_package/states_info.py
generated_demo_repo_1-0.0.0.dist-info/METADATA
generated_demo_repo_1-0.0.0.dist-info/WHEEL
generated_demo_repo_1-0.0.0.dist-info/top_level.txt
generated_demo_repo_1-0.0.0.dist-info/RECORD
