Metadata-Version: 2.1
Name: generated-demo-repo-1
Version: 0.0.0
Summary: Python package description for generated-demo-repo-1
Author-email: Amit Vikram Raj <82011740+avr2002@users.noreply.github.com>
License: MIT
Keywords: python
Classifier: Programming Language :: Python :: 3
Requires-Python: >=3.7
Requires-Dist: numpy
Requires-Dist: importlib-metadata; python_version >= "3.8"
Provides-Extra: dev
Requires-Dist: generated-demo-repo-1[release,static-code-qa,test]; extra == "dev"
Provides-Extra: release
Requires-Dist: build; extra == "release"
Requires-Dist: twine; extra == "release"
Provides-Extra: static-code-qa
Requires-Dist: pre-commit; extra == "static-code-qa"
Provides-Extra: test
Requires-Dist: pytest; extra == "test"
Requires-Dist: pytest-cov; extra == "test"
